activitypub_linked_data-0.0.1.dist-info/licenses/LICENSE
activitypub_linked_data-0.0.1.dist-info/licenses/NOTICE
ap/linked_data/__init__.py
ap/linked_data/contexts.py
ap/linked_data/loaders.py
activitypub_linked_data-0.0.1.dist-info/METADATA
activitypub_linked_data-0.0.1.dist-info/WHEEL
activitypub_linked_data-0.0.1.dist-info/top_level.txt
activitypub_linked_data-0.0.1.dist-info/RECORD
