Metadata-Version: 2.4
Name: activitypub-linked-data
Version: 0.0.1
Summary: JSON-LD context loader and RDF schema definitions for ActivityPub
Author-email: Raphael Lullis <raphael@mushroomlabs.com>
License-Expression: BSD-3-Clause
Keywords: activitypub,jsonld
Classifier: Intended Audience :: Developers
Classifier: Programming Language :: Python :: 3
Classifier: Programming Language :: Python :: 3.9
Classifier: Programming Language :: Python :: 3.10
Classifier: Programming Language :: Python :: 3.11
Classifier: Programming Language :: Python :: 3.12
Classifier: Programming Language :: Python :: 3.13
Classifier: Topic :: Internet :: WWW/HTTP
Requires-Python: <4,>=3.9
License-File: LICENSE
License-File: NOTICE
Requires-Dist: rdflib>=7.0.0
Dynamic: license-file
